flask_aceeditor/__init__.py
flask_aceeditor/static/js/ace.min.js
flask_aceeditor/static/js/brython.min.js
flask_aceeditor/static/js/brython_stdlib.min.js
flask_aceeditor/static/js/ext-beautify.min.js
flask_aceeditor/static/js/ext-language_tools.min.js
flask_aceeditor/static/js/ext-searchbox.min.js
flask_aceeditor/static/js/jquery-3.6.0.min.js
flask_aceeditor/static/js/mode-python.min.js
flask_aceeditor/static/js/python.min.js
flask_aceeditor/static/js/theme-monokai.min.js
flask_aceeditor/static/js/theme-xcode.min.js
Flask_AceEditor-1.0.7.dist-info/LICENSE
Flask_AceEditor-1.0.7.dist-info/METADATA
Flask_AceEditor-1.0.7.dist-info/WHEEL
Flask_AceEditor-1.0.7.dist-info/top_level.txt
Flask_AceEditor-1.0.7.dist-info/RECORD
