Metadata-Version: 2.1
Name: Flask-AceEditor
Version: 1.0.7
Summary: This is AceEditor on flask.
Home-page: https://github.com/lrsgzs/flask-aceeitor
Author: LRS
Author-email: liurongshuo2022@outlook.com
License: MIT
Keywords: flask extension lrspackages
Classifier: License :: OSI Approved :: MIT License
Classifier: Programming Language :: Python
Classifier: Programming Language :: Python :: 3
Classifier: Programming Language :: Python :: 3.7
Classifier: Programming Language :: Python :: Implementation :: CPython
Classifier: Programming Language :: Python :: Implementation :: PyPy
License-File: LICENSE
Requires-Dist: flask
